oyl/__init__.py
oyl/algorithm.py
oyl/drawings.py
oyl/infos.py
oyl/scores.py
oyl/utils.py
oyl/maskfiles/anhui.nc
oyl/maskfiles/aomen.nc
oyl/maskfiles/beijing.nc
oyl/maskfiles/china.nc
oyl/maskfiles/chongqing.nc
oyl/maskfiles/fujian.nc
oyl/maskfiles/gansu.nc
oyl/maskfiles/guangdong.nc
oyl/maskfiles/guangxi.nc
oyl/maskfiles/guizhou.nc
oyl/maskfiles/hainan.nc
oyl/maskfiles/hebei.nc
oyl/maskfiles/heilongjiang.nc
oyl/maskfiles/henan.nc
oyl/maskfiles/hubei.nc
oyl/maskfiles/hunan.nc
oyl/maskfiles/jiangsu.nc
oyl/maskfiles/jiangxi.nc
oyl/maskfiles/jilin.nc
oyl/maskfiles/liaoning.nc
oyl/maskfiles/neimenggu.nc
oyl/maskfiles/ningxia.nc
oyl/maskfiles/qinghai.nc
oyl/maskfiles/shandong.nc
oyl/maskfiles/shanghai.nc
oyl/maskfiles/shanxi1.nc
oyl/maskfiles/shanxi2.nc
oyl/maskfiles/sichuan.nc
oyl/maskfiles/taiwan.nc
oyl/maskfiles/tianjin.nc
oyl/maskfiles/xianggang.nc
oyl/maskfiles/xinjiang.nc
oyl/maskfiles/xizang.nc
oyl/maskfiles/yunnan.nc
oyl/maskfiles/zhejiang.nc
oyl/nn/CNN.py
oyl/nn/GA_MLP.py
oyl/nn/GA_RBF.py
oyl/nn/RBF.py
oyl/nn/__init__.py
oyl/shapefiles/TPBoundary_2500.dbf
oyl/shapefiles/TPBoundary_2500.shp
oyl/shapefiles/TPBoundary_2500.shx
oyl/shapefiles/TPBoundary_3000.dbf
oyl/shapefiles/TPBoundary_3000.shp
oyl/shapefiles/TPBoundary_3000.shx
oyl/shapefiles/anhui.dbf
oyl/shapefiles/anhui.shp
oyl/shapefiles/anhui.shx
oyl/shapefiles/aomen.dbf
oyl/shapefiles/aomen.shp
oyl/shapefiles/aomen.shx
oyl/shapefiles/beijing.dbf
oyl/shapefiles/beijing.shp
oyl/shapefiles/beijing.shx
oyl/shapefiles/china_country.dbf
oyl/shapefiles/china_country.shp
oyl/shapefiles/china_country.shx
oyl/shapefiles/china_nine_dotted_line.dbf
oyl/shapefiles/china_nine_dotted_line.shp
oyl/shapefiles/china_nine_dotted_line.shx
oyl/shapefiles/chongqing.dbf
oyl/shapefiles/chongqing.shp
oyl/shapefiles/chongqing.shx
oyl/shapefiles/cnhimap.dbf
oyl/shapefiles/cnhimap.shp
oyl/shapefiles/cnhimap.shx
oyl/shapefiles/fujian.dbf
oyl/shapefiles/fujian.shp
oyl/shapefiles/fujian.shx
oyl/shapefiles/gansu.dbf
oyl-2.6.2.dist-info/METADATA
oyl-2.6.2.dist-info/WHEEL
oyl-2.6.2.dist-info/top_level.txt
oyl-2.6.2.dist-info/RECORD
