Metadata-Version: 2.4
Name: oyl
Version: 2.6.2
Author: Lin Ouyang
Requires-Dist: numpy
Requires-Dist: matplotlib
Requires-Dist: pandas
Requires-Dist: pyshp
Dynamic: author
Dynamic: requires-dist
